bettermoments/__init__.py
bettermoments/collapse_cube.py
bettermoments/collapse_cube_old.py
bettermoments/methods.py
bettermoments/methods_old.py
bettermoments/quadratic.py
bettermoments/tests/__init__.py
bettermoments/tests/tests.py
bettermoments-1.4.3.dist-info/LICENSE.md
bettermoments-1.4.3.dist-info/METADATA
bettermoments-1.4.3.dist-info/WHEEL
bettermoments-1.4.3.dist-info/entry_points.txt
bettermoments-1.4.3.dist-info/top_level.txt
bettermoments-1.4.3.dist-info/zip-safe
bettermoments-1.4.3.dist-info/RECORD
