Metadata-Version: 2.1
Name: bettermoments
Version: 1.4.3
Summary: Robust moment map making.
Home-page: https://github.com/richteague/bettermoments
Author: Richard Teague & Daniel Foreman-Mackey
Author-email: richard.d.teague@cfa.harvard.edu
License: LICENSE.md
Platform: UNKNOWN
Classifier: Development Status :: 5 - Production/Stable
Classifier: Intended Audience :: Developers
Classifier: Intended Audience :: Science/Research
Classifier: License :: OSI Approved :: MIT License
Classifier: Operating System :: OS Independent
Classifier: Programming Language :: Python
Requires-Dist: numpy
Requires-Dist: astropy
Requires-Dist: argparse
Requires-Dist: tqdm
